{
  "__type__": "cc.Mesh",
  "_name": "",
  "_objFlags": 0,
  "_native": ".bin",
  "_struct": {
    "primitives": [
      {
        "primitiveMode": 7,
        "vertexBundelIndices": [
          0
        ],
        "indexView": {
          "offset": 14728,
          "length": 3216,
          "count": 804,
          "stride": 4
        }
      }
    ],
    "vertexBundles": [
      {
        "view": {
          "offset": 0,
          "length": 14728,
          "count": 263,
          "stride": 56
        },
        "attributes": [
          {
            "name": "a_position",
            "format": 32,
            "isNormalized": false
          },
          {
            "name": "a_normal",
            "format": 32,
            "isNormalized": false
          },
          {
            "name": "a_texCoord",
            "format": 21,
            "isNormalized": false
          },
          {
            "name": "a_tangent",
            "format": 44,
            "isNormalized": false
          },
          {
            "name": "a_texCoord1",
            "format": 21,
            "isNormalized": false
          }
        ]
      }
    ],
    "minPosition": {
      "__type__": "cc.Vec3",
      "x": -0.7991340160369873,
      "y": -0.42175018787384033,
      "z": 1.1831458124333949e-7
    },
    "maxPosition": {
      "__type__": "cc.Vec3",
      "x": 0.9116226434707642,
      "y": 0.42175018787384033,
      "z": 0.928779125213623
    }
  },
  "_hash": 943117032,
  "_allowDataAccess": true
}